{
  "fig01": {
    "customers": 88,
    "green_customers": 12,
    "top_demand_customer_id": 8,
    "top_demand_index_0_100": 97.428,
    "green_zone_radius_km_from_boundary_max": 10.0
  },
  "fig02": {
    "raw_orders": 2169,
    "active_customers": 88,
    "virtual_service_nodes": 148,
    "active_green_customers": 12,
    "green_service_nodes": 19,
    "split_customers": 36
  },
  "fig03": {
    "periods": 7,
    "load_ratios": [
      0.0,
      0.5,
      1.0
    ],
    "fuel_min_max": [
      25.27,
      41.36
    ],
    "ev_min_max": [
      33.73,
      47.49
    ]
  },
  "fig04": {
    "problem1_arcs": 264,
    "vehicle_types": [
      "E1",
      "F1"
    ],
    "late_trips_trip_max_late_gt0": 4,
    "max_trip_late_min": 31.6
  },
  "fig05": {
    "p1_total_cost": 48644.68,
    "p2_total_cost": 49239.78,
    "delta_cost": 595.1,
    "p1_carbon_kg": 8337.49,
    "p2_carbon_kg": 8156.49,
    "p2_policy_conflict_count": "0"
  },
  "fig06": {
    "problem1_screened_under_p2_policy": 12,
    "problem2_formal": 0
  },
  "fig07": {
    "variants": [
      "default_split",
      "green_e2_adaptive",
      "green_hotspot_partial",
      "policy_ops_ev_reservation_p500"
    ],
    "default_total_cost": 49239.78,
    "all_policy_conflict_count": [
      0,
      0,
      0,
      0
    ],
    "service_quality_variant_max_late_min": 5.93
  },
  "fig08": {
    "scenarios": [
      "cancel_future_order_1030",
      "new_green_order_1330",
      "time_window_pull_forward_1500",
      "address_change_proxy_1200"
    ],
    "delta_total_cost": [
      -528.51,
      -2.42,
      23.57,
      -32.31
    ],
    "policy_conflict_count": [
      0,
      0,
      0,
      0
    ],
    "changed_stop_count": [
      1,
      2,
      1,
      2
    ]
  },
  "fig09": {
    "affected_trip_vehicle": [
      "T0051 / F1-025",
      "T0038 / E1-004",
      "T0102 / F1-004",
      "T0026 / E1-008"
    ],
    "frozen_segment_rows_by_scenario": {
      "address_change_proxy_1200": 41,
      "cancel_future_order_1030": 30,
      "new_green_order_1330": 49,
      "time_window_pull_forward_1500": 70
    }
  },
  "fig10": {
    "cases": [
      "P1 formal",
      "P2 formal",
      "cancel_future_order_1030",
      "new_green_order_1330",
      "time_window_pull_forward_1500",
      "address_change_proxy_1200"
    ],
    "coverage_all_true": true,
    "capacity_all_true": true,
    "physical_chain_all_true": true,
    "non_na_policy_conflict_counts": [
      0,
      0,
      0,
      0,
      0
    ],
    "max_late_min_values": [
      31.6,
      129.44,
      129.44,
      129.44,
      129.44,
      129.44
    ]
  }
}